{
  "document_id": "HOUSE_OVERSIGHT_019127",
  "filename": "IMAGES-005-HOUSE_OVERSIGHT_019127.txt",
  "text": "ERSON\n\nunning off to do something\nsr already that there’s nothing\n\ngrant—a self-made man who\nwise to the ways of the world\nughters. They're good girls, he\nhe knows, they don’t drink.\nlove clothes and, especially,\ntado, Maroon 5, the boy band\ny loves California, which she’s\nShe just knows she'll live there\nth her father as long as Mary\n\nchores.\ne meantime, is the crowd that\n\nsible than most American boys\nis another story. Mary’s father\nld have liked her even less had\nms.\n\nsid Mary, she can make more\na day: “This guy in Palm Beach.\nrplane. He owns an island, you\n\ninland, away from the Florida\n‘beyond the dull, scrubby flat-\n\nying details, and dialogue have been\n\nms ae Fa =\n\nFirtHy RicH\n\nlands and strip malls she’s grown up around. There’s so much\nthat she wants to do and see. But for her the Gold Coast, twenty\nmiles away, might as well be another country.\n“Yes,” she had said, without even thinking about it.\nThen there was Joe to contend with.\n“Who is this guy?” Joe had said, shaking his head. “You don't\nknow a thing about him.”\n“Hundreds of dollars,” Mary had whispered. She couldn't\nquite look at Joe, but she was firm: “I can make that in one hour.”\nJoe seemed to think they were actually talking about it. A\nconversation — some back-and-forth. But the thought of not going\nhadn't even crossed Mary’s mind. If anything, she hoped that it\nwould become a regular thing.\n“To rub his feet? Are you kidding? If you’re not worried about\nit, why haven't you told your dad?”\n“It’s your cousin, Joe! Some girls go three times a week.”\n“The guy’s feet must be killing him.”\n“Shut up!”\n“Tell your father.”\n“You know how Dad is. You don't tell your parents\neverything.”\n“Tm not going to some freak’s mansion to rub his feet.”\n“That’s right. I am.”\n“And if I told your father? Or mine?”\n“You'd never see me again.”\nMary felt bad as she said it. She felt bad for lying.\nShe knew that it would be more than a foot rub.\nWendy had told her that much, at least.\n\nI]\n\nHOUSE_OVERSIGHT_019127",
  "metadata": {
    "original_filename": "IMAGES-005-HOUSE_OVERSIGHT_019127.txt",
    "source_dataset": "huggingface:tensonaut/EPSTEIN_FILES_20K",
    "character_count": 1987,
    "word_count": 366,
    "line_count": 68,
    "import_date": "2025-11-19T21:47:44.660528",
    "prefix": "IMAGES-005"
  }
}