{
  "document_id": "HOUSE_OVERSIGHT_031364",
  "filename": "IMAGES-011-HOUSE_OVERSIGHT_031364.txt",
  "text": "ee\nSe\n\nNOBEL CHARITABLE TRUST\n\nBasic Development Plan of the Convention\n\n* Unauthorized use of information, postings and distributions are strictly prohibited. For information, please contact the Nobel Charitable Trust at info@nobelcharitabletrust.org\n\n5\nHOUSE_OVERSIGHT_031364",
  "metadata": {
    "original_filename": "IMAGES-011-HOUSE_OVERSIGHT_031364.txt",
    "source_dataset": "huggingface:tensonaut/EPSTEIN_FILES_20K",
    "character_count": 277,
    "word_count": 34,
    "line_count": 11,
    "import_date": "2025-11-19T21:47:46.332477",
    "prefix": "IMAGES-011"
  }
}