{
  "document_id": "HOUSE_OVERSIGHT_029872",
  "filename": "IMAGES-010-HOUSE_OVERSIGHT_029872.txt",
  "text": "apnews.com / JOHNSON LAI HONG KONG (AP) — Police said they\nhad arrested 13 people after the protests on Monday’s anniversary of\n\nHong Kong’s return to China, including one man...\n\nActing DHS chief orders immediate\ninvestigation into offensive posts\nallegedly written by Border Patrol\nagents\n\nHOUSE_OVERSIGHT_029872",
  "metadata": {
    "original_filename": "IMAGES-010-HOUSE_OVERSIGHT_029872.txt",
    "source_dataset": "huggingface:tensonaut/EPSTEIN_FILES_20K",
    "character_count": 314,
    "word_count": 46,
    "line_count": 11,
    "import_date": "2025-11-19T21:47:48.491001",
    "prefix": "IMAGES-010"
  }
}