{
  "document_id": "HOUSE_OVERSIGHT_027591",
  "filename": "IMAGES-009-HOUSE_OVERSIGHT_027591.txt",
  "text": "Sender: e:jeeitunes@gmail.com\n\nTime: 03/07/19\nFlags: 1085445\nIs Read: No\n\nIs Invitation:\n\nGUID: 709D925E\n\n25\n\nMessage: Don't\n\n04\n\nNo\n\n2:13:00 AM (573653580)\n\nD1DD-4B4F-B55C-A75A286E3870\n\nyou have stroke with her\n\nsender: i’\n\nTime: 03/07/19 04:15:26 AM (573653726)\n\nFlags: 1060865\nIs Read: Yes\n\nIs Invitation:\n\nGUID: AA683707-F7A7-4\n\nNo\n\nr\n\n(ES-A51C-0009BC35C139\n\nMessage: Not on this topic -- zero\n\nSender: e:jeeitunes@gmail.com\n\nTime: 03/07/19 04:16:20 AM (573653780)\n\nFlags: 1085445\nITs Read: No\n\nIs Invitation:\n\nGUID: 7963A0D7-4C]\n\nNo\n\nE9-41BO-A5C1-98BFE52AE73B\n\nMessage: understood.\n\nSender: e:jeeitunes@gmail.com\n\nTime: 03/07/19 04:16:41 AM (573653801)\n\nFlags: 1085445\nTs Read: No\n\nIs Invitation:\n\nGUID: 7A4CC3B5-54]\n\nNo\n\nE8-4961-B9F5-3CBF5837F6E5\n\nMessage: Is there anything I can do except for perfecting the art of being a punching\n\nbag\n\nSender: Zi’\n\nTime: 03/07/19 04:36:36 AM (573654996)\n\nFlags: 1060865\nIs Read: Yes\n\nIs Invitation:\n\nNo\n\nGUID: C2CC23DD-9C90-4594-8D17-AF22F16E82DC\n\nMessage: It's bad -- never seen anything like it\n\nSender: e:jeeitunes@gmail.com\n\nHOUSE_OVERSIGHT_027591",
  "metadata": {
    "original_filename": "IMAGES-009-HOUSE_OVERSIGHT_027591.txt",
    "source_dataset": "huggingface:tensonaut/EPSTEIN_FILES_20K",
    "character_count": 1095,
    "word_count": 137,
    "line_count": 97,
    "import_date": "2025-11-19T21:47:44.637276",
    "prefix": "IMAGES-009"
  }
}