{
  "document_id": "HOUSE_OVERSIGHT_029137",
  "filename": "IMAGES-010-HOUSE_OVERSIGHT_029137.txt",
  "text": "From: Robert Kuh —_— |\n\nSent: 12/31/2017 9:32:53 PM\nTo: jeffrey E. [jeevacation@gmail.com]\nSubject: Re: Kuhn - Math, Breakthroughs\n\nImportance: — High\n\nOK\n\nOn Dec 31, 2017, at 4:32 PM, jeffrey E. <jeevacation@gmail.com> wrote:\n5 min\n\nOn Sun, Dec 31, 2017 at 4:21 PM, Robert Kuhn ; wrote:\nReady when you are - let me know and I can call.\n\nFaceTime = email.\n\nOn Dec 31, 2017, at 5:50 AM, jeffrey E. <jeevacation@gmail.com> wrote:\neither\n\nOn Sat, Dec 30, 2017 at 8:58 PM, Robert Kuhn qq wrote:\nAfter 4 good.\n\nSkype? FaceTime? Phone?\n\nOn Dec 30, 2017, at 8:57 PM, jeffrey E. <jeevacation@gmail.com> wrote:\nguest s here until 4. after good\nOn Sat, Dec 30, 2017 at 8:04 PM, Robert Kuhn > wrote:\n\nTomorrow Sunday after 1:00 pm? Flexible. Anytime.\nSkype? FaceTime? Phone?\n\nOn Dec 29, 2017, at 3:27 PM, jeffrey E. <jeevacation@gmail.com> wrote:\n\nweekend easy\n\nOn Fri, Dec 29, 2017 at 3:21 PM, Robert Kuhn <q wrote:\nTerrific; looking forward.\n\nExcited to go through math candidates on the list, others too.\n\nHOUSE_OVERSIGHT_029137",
  "metadata": {
    "original_filename": "IMAGES-010-HOUSE_OVERSIGHT_029137.txt",
    "source_dataset": "huggingface:tensonaut/EPSTEIN_FILES_20K",
    "character_count": 1020,
    "word_count": 173,
    "line_count": 43,
    "import_date": "2025-11-19T21:47:48.905779",
    "prefix": "IMAGES-010"
  }
}