{
  "document_id": "HOUSE_OVERSIGHT_020601",
  "filename": "IMAGES-006-HOUSE_OVERSIGHT_020601.txt",
  "text": "uoneiadoo ALE\n\nJeuoeuseU| 4104 BIO\n\nseausis\nAlevIW Jo Awapeoy\n\nAqss9alun\nasuajag jeuoneN\n\nasuzjeq\nJeuonen jo AnsiuiA\n\nneaing\n99ua8)|/91uU]\n\nquawiedeq\nHES UOT\n\nquawyiedaq\n\nUOJSSIWILUOD\nAUeUIIN [213UaD\n\nsaSueyoxa aayIWWOD\nAueyusweljied suleyiy udIa104\n\nssau#u0)\nsaidead |eUSeN\n\nASojouysal pue\n\nAjuaBy uopesadoo\n\nAqunsasg\na7e1S JO ANSIUIIN\n\nsan |suealun\n\nuoljeanpy jo Ans!\n\na2uags JO ANSIUI\n\nuequeH\n\nquewdojsasq jeucneusequy\n\nwinioy\noeog\nSIIEWY\n\nUBlaJ04 Jo ANsiulA)\n\nwistnoy pue\n@ININD JO ANSIUlW\n\n[punop aye15\n\n5S] epuesedaid\npue uoyeonpy\n\nneaung\n\nquowedsq\nepuegedoig\n\nS340\nepuesedoid jeuseixg\n\nOs1\nepuegedolg jeueDxg\n\nS2YO suleyy UsIa104\n\nUOISS|UIWIOD\nSHBYYy UBIBI04\n\nSOWO SHEL\n@SOUIYD SeasIaAD\n\nYNdddD\n\njuawyedaq\nJOA, UOJ peuy\n\n9$] ody payun\n\naaywUoD\n[23D ddd\n\noungulied do>-\n\nAdeisneaing suoineiado aduanyu] asaulyD\n\naaywwo>\nasauly) seasiaAQ\n\nHOUSE_OVERSIGHT_020601",
  "metadata": {
    "original_filename": "IMAGES-006-HOUSE_OVERSIGHT_020601.txt",
    "source_dataset": "huggingface:tensonaut/EPSTEIN_FILES_20K",
    "character_count": 866,
    "word_count": 109,
    "line_count": 98,
    "import_date": "2025-11-19T21:47:47.592370",
    "prefix": "IMAGES-006"
  }
}